fasthtml_cli/__init__.py
fasthtml_cli/cli.py
fasthtml_cli/fasthtml_templates/basic.py
fhx-0.1.1.dist-info/METADATA
fhx-0.1.1.dist-info/WHEEL
fhx-0.1.1.dist-info/entry_points.txt
fhx-0.1.1.dist-info/RECORD
